transformars/__init__.py
transformars/bert.safertensors
transformars/utils.py
transformars-4.42.3.post4.dist-info/METADATA
transformars-4.42.3.post4.dist-info/WHEEL
transformars-4.42.3.post4.dist-info/top_level.txt
transformars-4.42.3.post4.dist-info/RECORD
