Metadata-Version: 2.1
Name: transformars
Version: 4.42.3.post4
Summary: A drop-in replacement for the transformers library
Home-page: https://github.com/sudoaza/transformars
Author: Robert Paulson
Author-email: bob@fclub.org
Classifier: Programming Language :: Python :: 3
Classifier: License :: OSI Approved :: MIT License
Classifier: Operating System :: OS Independent
Requires-Python: >=3.6
Requires-Dist: transformers ==4.42.3
